odoo9_addon_report_qweb_pdf_watermark-9.0.1.0.0-py2.7-nspkg.pth
odoo_addons/report_qweb_pdf_watermark/__openerp__.py
odoo_addons/report_qweb_pdf_watermark/__init__.py
odoo_addons/report_qweb_pdf_watermark/README.rst
odoo_addons/report_qweb_pdf_watermark/models/report.py
odoo_addons/report_qweb_pdf_watermark/models/__init__.py
odoo_addons/report_qweb_pdf_watermark/models/ir_actions_report_xml.py
odoo_addons/report_qweb_pdf_watermark/views/ir_actions_report_xml.xml
odoo_addons/report_qweb_pdf_watermark/tests/test_report_qweb_pdf_watermark.py
odoo_addons/report_qweb_pdf_watermark/tests/__init__.py
odoo_addons/report_qweb_pdf_watermark/demo/report.xml
odoo_addons/report_qweb_pdf_watermark/static/description/icon.png
odoo9_addon_report_qweb_pdf_watermark-9.0.1.0.0.dist-info/top_level.txt
odoo9_addon_report_qweb_pdf_watermark-9.0.1.0.0.dist-info/WHEEL
odoo9_addon_report_qweb_pdf_watermark-9.0.1.0.0.dist-info/RECORD
odoo9_addon_report_qweb_pdf_watermark-9.0.1.0.0.dist-info/metadata.json
odoo9_addon_report_qweb_pdf_watermark-9.0.1.0.0.dist-info/DESCRIPTION.rst
odoo9_addon_report_qweb_pdf_watermark-9.0.1.0.0.dist-info/METADATA
odoo9_addon_report_qweb_pdf_watermark-9.0.1.0.0.dist-info/namespace_packages.txt
